urlshortener/__init__.py
urlshortener/admin.py
urlshortener/apps.py
urlshortener/urls.py
urlshortener/extra/__init__.py
urlshortener/extra/shortcodes.py
urlshortener/extra/__pycache__/__init__.cpython-38.pyc
urlshortener/extra/__pycache__/shortcodes.cpython-38.pyc
urlshortener/managers/ShortenerModelManager.py
urlshortener/managers/__init__.py
urlshortener/managers/__pycache__/ShortenerModelManager.cpython-38.pyc
urlshortener/managers/__pycache__/__init__.cpython-38.pyc
urlshortener/migrations/0001_initial.py
urlshortener/migrations/__init__.py
urlshortener/migrations/__pycache__/0001_initial.cpython-38.pyc
urlshortener/migrations/__pycache__/__init__.cpython-38.pyc
urlshortener/modeladmins/ShortenerModelAdmin.py
urlshortener/modeladmins/__init__.py
urlshortener/modeladmins/__pycache__/ShortenerModelAdmin.cpython-38.pyc
urlshortener/modeladmins/__pycache__/__init__.cpython-38.pyc
urlshortener/modelforms/ShortenerModelForm.py
urlshortener/modelforms/URLOnlyShortenerModelForm.py
urlshortener/modelforms/__init__.py
urlshortener/modelforms/__pycache__/ShortenerModelForm.cpython-38.pyc
urlshortener/modelforms/__pycache__/URLOnlyShortenerModelForm.cpython-38.pyc
urlshortener/modelforms/__pycache__/__init__.cpython-38.pyc
urlshortener/models/ShortenerModel.py
urlshortener/models/__init__.py
urlshortener/models/__pycache__/ShortenerModel.cpython-38.pyc
urlshortener/models/__pycache__/__init__.cpython-38.pyc
urlshortener/querysets/ShortenerModelQuerySet.py
urlshortener/querysets/__init__.py
urlshortener/querysets/__pycache__/ShortenerModelQuerySet.cpython-38.pyc
urlshortener/querysets/__pycache__/__init__.cpython-38.pyc
urlshortener/templates/djangoadmin/urlshortener/homepage_view.html
urlshortener/templates/djangoadmin/urlshortener/url_create_view.html
urlshortener/templates/djangoadmin/urlshortener/url_delete_dashboard.html
urlshortener/templates/djangoadmin/urlshortener/url_detail_dashboard.html
urlshortener/templates/djangoadmin/urlshortener/url_list_dashboard.html
django_urlshortener-2.0.0.dist-info/License
django_urlshortener-2.0.0.dist-info/METADATA
django_urlshortener-2.0.0.dist-info/WHEEL
django_urlshortener-2.0.0.dist-info/top_level.txt
django_urlshortener-2.0.0.dist-info/RECORD
